hydrostab/__init__.py
hydrostab/experimental.py
hydrostab/ras.py
hydrostab/utils.py
hydrostab-0.2.0.dist-info/licenses/LICENSE
hydrostab-0.2.0.dist-info/METADATA
hydrostab-0.2.0.dist-info/WHEEL
hydrostab-0.2.0.dist-info/top_level.txt
hydrostab-0.2.0.dist-info/RECORD
