Metadata-Version: 2.4
Name: hydrostab
Version: 0.2.0
Summary: Evaluation of hydrograph stability, detecting oscillations in data from hydrodynamic models.
Project-URL: repository, https://github.com/fema-ffrd/hydrostab
Classifier: Development Status :: 4 - Beta
Classifier: Intended Audience :: Developers
Classifier: License :: OSI Approved :: MIT License
Classifier: Programming Language :: Python :: 3
Classifier: Programming Language :: Python :: 3.9
Classifier: Programming Language :: Python :: 3.10
Classifier: Programming Language :: Python :: 3.11
Classifier: Programming Language :: Python :: 3.12
License-File: LICENSE
Requires-Dist: pandas
Provides-Extra: ras
Requires-Dist: rashdf; extra == "ras"
Provides-Extra: exp
Requires-Dist: scipy; extra == "exp"
Provides-Extra: dev
Requires-Dist: pre-commit; extra == "dev"
Requires-Dist: ruff; extra == "dev"
Requires-Dist: pytest; extra == "dev"
Requires-Dist: pytest-cov; extra == "dev"
Provides-Extra: nb
Requires-Dist: jupyterlab; extra == "nb"
Requires-Dist: jupytext; extra == "nb"
Requires-Dist: ipywidgets; extra == "nb"
Requires-Dist: matplotlib; extra == "nb"
Requires-Dist: rashdf; extra == "nb"
Dynamic: license-file
